setup.py
torchlight/__init__.py
torchlight.egg-info/PKG-INFO
torchlight.egg-info/SOURCES.txt
torchlight.egg-info/dependency_links.txt
torchlight.egg-info/top_level.txt