Metadata-Version: 1.0
Name: torchlight
Version: 0.0.1
Summary: Torch Light
Home-page: UNKNOWN
Author: UNKNOWN
Author-email: UNKNOWN
License: MIT
Platform: UNKNOWN
